cnjfacil/__init__.py
cnjfacil/exceptions.py
cnjfacil/extrator.py
CNJFacil-0.1.6.dist-info/LICENSE
CNJFacil-0.1.6.dist-info/METADATA
CNJFacil-0.1.6.dist-info/WHEEL
CNJFacil-0.1.6.dist-info/top_level.txt
CNJFacil-0.1.6.dist-info/RECORD
