Metadata-Version: 2.1
Name: CNJFacil
Version: 0.1.6
Summary: Conjunto de ferramentas para trabalhar com CNJ
Home-page: https://github.com/mbodock/cnjfacil
Author: Marcus Bodock
Author-email: mbodock@gmail.com
License: MIT
Platform: UNKNOWN
Classifier: Development Status :: 2 - Pre-Alpha
Classifier: License :: OSI Approved :: MIT License
Classifier: Operating System :: OS Independent
Classifier: Programming Language :: Python
Classifier: Programming Language :: Python :: 2
Classifier: Programming Language :: Python :: 2.7
Classifier: Programming Language :: Python :: 3
Classifier: Programming Language :: Python :: 3.5
Classifier: Topic :: Internet :: WWW/HTTP
Classifier: Topic :: Software Development :: Libraries :: Python Modules
